aiohutils/__init__.py
aiohutils/pd.py
aiohutils/server.py
aiohutils/session.py
aiohutils-0.22.4.dist-info/WHEEL
aiohutils-0.22.4.dist-info/METADATA
aiohutils-0.22.4.dist-info/RECORD
