Metadata-Version: 2.3
Name: aiohutils
Version: 0.22.4
Summary: A small library to for aiohttp projects.
Author: 5j9
Author-email: 5j9 <5j9@users.noreply.github.com>
License: GNU General Public License v3 (GPLv3)
Classifier: License :: OSI Approved :: GNU General Public License v3 (GPLv3)
Classifier: Programming Language :: Python :: 3.10
Requires-Dist: aiohttp[speedups]
Requires-Dist: html5lib
Requires-Dist: pandas[pyarrow]>=2.2.1
Requires-Python: >=3.12
Project-URL: Homepage, https://github.com/5j9/aiohutils
